{
  "equipo": "C.F. Extramurs Valencia 'A'",
  "grupo": "Lliga Regular Grup 6",
  "ultima_actualizacion": "2026-02-11T06:57:51.756783",
  "proximo_partido": {
    "jornada": 6,
    "id_partido": "26450761",
    "fecha": "2026-02-14",
    "hora": "11:00",
    "local": "C.F. Inter San José Valencia 'C'",
    "visitante": "C.F. Extramurs Valencia 'A'",
    "campo": "Campo de Fútbol Mpal. de Beniferri F-8 Campo 1(HA)",
    "resultado": null,
    "es_local": false,
    "victoria": null,
    "maps_url": "https://www.google.com/maps/search/?api=1&query=Campo%20de%20F%C3%BAtbol%20Mpal.%20de%20Beniferri%20F-8%20Campo%201%28HA%29%2C%20Valencia%2C%20Espa%C3%B1a"
  },
  "ultimos_resultados": [
    {
      "jornada": 5,
      "id_partido": "26450755",
      "fecha": "2026-02-07",
      "hora": "17:30",
      "local": "C.F. Extramurs Valencia 'A'",
      "visitante": "S.F.A.C. San Antonio Benagéber 'A'",
      "campo": "Campo Tramo III del Turia F-8(HA)",
      "resultado": "5-1",
      "es_local": true,
      "victoria": true,
      "maps_url": "https://www.google.com/maps/search/?api=1&query=Campo%20Tramo%20III%20del%20Turia%20F-8%28HA%29%2C%20Valencia%2C%20Espa%C3%B1a"
    },
    {
      "jornada": 4,
      "id_partido": "26450750",
      "fecha": "2026-01-31",
      "hora": "10:15",
      "local": "Los Silos C.F. - Promises Valencia 'A'",
      "visitante": "C.F. Extramurs Valencia 'A'",
      "campo": "Campo Las Oliveras F-8 Burjassot(T)",
      "resultado": "2-4",
      "es_local": false,
      "victoria": true,
      "maps_url": "https://www.google.com/maps/search/?api=1&query=Campo%20Las%20Oliveras%20F-8%20Burjassot%28T%29%2C%20Valencia%2C%20Espa%C3%B1a"
    },
    {
      "jornada": 3,
      "id_partido": "26450744",
      "fecha": "2026-01-24",
      "hora": "11:15",
      "local": "C.F. Extramurs Valencia 'A'",
      "visitante": "C.F. Cracks 'B'",
      "campo": "Campo Tramo III del Turia F-8(HA)",
      "resultado": "5-3",
      "es_local": true,
      "victoria": true,
      "maps_url": "https://www.google.com/maps/search/?api=1&query=Campo%20Tramo%20III%20del%20Turia%20F-8%28HA%29%2C%20Valencia%2C%20Espa%C3%B1a"
    },
    {
      "jornada": 2,
      "id_partido": "26450739",
      "fecha": "2026-01-18",
      "hora": "10:15",
      "local": "C.F. Extramurs Valencia 'A'",
      "visitante": "Vilamarxant C.F.",
      "campo": "Campo Tramo III del Turia F-8(HA)",
      "resultado": "6-7",
      "es_local": true,
      "victoria": false,
      "maps_url": "https://www.google.com/maps/search/?api=1&query=Campo%20Tramo%20III%20del%20Turia%20F-8%28HA%29%2C%20Valencia%2C%20Espa%C3%B1a"
    },
    {
      "jornada": 1,
      "id_partido": "26450734",
      "fecha": "2026-01-11",
      "hora": "09:30",
      "local": "Atlètic Vallbonense 'A'",
      "visitante": "C.F. Extramurs Valencia 'A'",
      "campo": "Polideportivo Mpal. Salvador Marti F-8 Campo 1 Pobla Vallbona(HA)",
      "resultado": "1-0",
      "es_local": false,
      "victoria": false,
      "maps_url": "https://www.google.com/maps/search/?api=1&query=Polideportivo%20Mpal.%20Salvador%20Marti%20F-8%20Campo%201%20Pobla%20Vallbona%28HA%29%2C%20Valencia%2C%20Espa%C3%B1a"
    }
  ],
  "clasificacion": [
    {
      "posicion": 1,
      "equipo": "C.F. Inter San José Valencia 'C'",
      "puntos": 12,
      "pj": 4,
      "pg": 4,
      "pe": 0,
      "pp": 0
    },
    {
      "posicion": 2,
      "equipo": "Atlètic Vallbonense 'A'",
      "puntos": 12,
      "pj": 4,
      "pg": 4,
      "pe": 0,
      "pp": 0
    },
    {
      "posicion": 3,
      "equipo": "Vilamarxant C.F.",
      "puntos": 10,
      "pj": 5,
      "pg": 3,
      "pe": 1,
      "pp": 1
    },
    {
      "posicion": 4,
      "equipo": "C.F. Extramurs Valencia 'A'",
      "puntos": 9,
      "pj": 5,
      "pg": 3,
      "pe": 0,
      "pp": 2
    },
    {
      "posicion": 5,
      "equipo": "Los Silos C.F. - Promises Valencia 'A'",
      "puntos": 9,
      "pj": 5,
      "pg": 3,
      "pe": 0,
      "pp": 2
    },
    {
      "posicion": 6,
      "equipo": "Paterna C.F. 'A'",
      "puntos": 6,
      "pj": 5,
      "pg": 2,
      "pe": 0,
      "pp": 3
    },
    {
      "posicion": 7,
      "equipo": "S.F.A.C. San Antonio Benagéber 'A'",
      "puntos": 6,
      "pj": 5,
      "pg": 2,
      "pe": 0,
      "pp": 3
    },
    {
      "posicion": 8,
      "equipo": "C.F. Torre Levante 'A'",
      "puntos": 4,
      "pj": 5,
      "pg": 1,
      "pe": 1,
      "pp": 3
    },
    {
      "posicion": 9,
      "equipo": "C.F. Cracks 'B'",
      "puntos": 3,
      "pj": 5,
      "pg": 1,
      "pe": 0,
      "pp": 4
    },
    {
      "posicion": 10,
      "equipo": "C.F. Històrics de València 'C'",
      "puntos": 0,
      "pj": 5,
      "pg": 0,
      "pe": 0,
      "pp": 5
    }
  ],
  "todos_partidos": [
    {
      "jornada": 1,
      "id_partido": "26450734",
      "fecha": "2026-01-11",
      "hora": "09:30",
      "local": "Atlètic Vallbonense 'A'",
      "visitante": "C.F. Extramurs Valencia 'A'",
      "campo": "Polideportivo Mpal. Salvador Marti F-8 Campo 1 Pobla Vallbona(HA)",
      "resultado": "1-0",
      "es_local": false,
      "victoria": false,
      "maps_url": "https://www.google.com/maps/search/?api=1&query=Polideportivo%20Mpal.%20Salvador%20Marti%20F-8%20Campo%201%20Pobla%20Vallbona%28HA%29%2C%20Valencia%2C%20Espa%C3%B1a"
    },
    {
      "jornada": 2,
      "id_partido": "26450739",
      "fecha": "2026-01-18",
      "hora": "10:15",
      "local": "C.F. Extramurs Valencia 'A'",
      "visitante": "Vilamarxant C.F.",
      "campo": "Campo Tramo III del Turia F-8(HA)",
      "resultado": "6-7",
      "es_local": true,
      "victoria": false,
      "maps_url": "https://www.google.com/maps/search/?api=1&query=Campo%20Tramo%20III%20del%20Turia%20F-8%28HA%29%2C%20Valencia%2C%20Espa%C3%B1a"
    },
    {
      "jornada": 3,
      "id_partido": "26450744",
      "fecha": "2026-01-24",
      "hora": "11:15",
      "local": "C.F. Extramurs Valencia 'A'",
      "visitante": "C.F. Cracks 'B'",
      "campo": "Campo Tramo III del Turia F-8(HA)",
      "resultado": "5-3",
      "es_local": true,
      "victoria": true,
      "maps_url": "https://www.google.com/maps/search/?api=1&query=Campo%20Tramo%20III%20del%20Turia%20F-8%28HA%29%2C%20Valencia%2C%20Espa%C3%B1a"
    },
    {
      "jornada": 4,
      "id_partido": "26450750",
      "fecha": "2026-01-31",
      "hora": "10:15",
      "local": "Los Silos C.F. - Promises Valencia 'A'",
      "visitante": "C.F. Extramurs Valencia 'A'",
      "campo": "Campo Las Oliveras F-8 Burjassot(T)",
      "resultado": "2-4",
      "es_local": false,
      "victoria": true,
      "maps_url": "https://www.google.com/maps/search/?api=1&query=Campo%20Las%20Oliveras%20F-8%20Burjassot%28T%29%2C%20Valencia%2C%20Espa%C3%B1a"
    },
    {
      "jornada": 5,
      "id_partido": "26450755",
      "fecha": "2026-02-07",
      "hora": "17:30",
      "local": "C.F. Extramurs Valencia 'A'",
      "visitante": "S.F.A.C. San Antonio Benagéber 'A'",
      "campo": "Campo Tramo III del Turia F-8(HA)",
      "resultado": "5-1",
      "es_local": true,
      "victoria": true,
      "maps_url": "https://www.google.com/maps/search/?api=1&query=Campo%20Tramo%20III%20del%20Turia%20F-8%28HA%29%2C%20Valencia%2C%20Espa%C3%B1a"
    },
    {
      "jornada": 6,
      "id_partido": "26450761",
      "fecha": "2026-02-14",
      "hora": "11:00",
      "local": "C.F. Inter San José Valencia 'C'",
      "visitante": "C.F. Extramurs Valencia 'A'",
      "campo": "Campo de Fútbol Mpal. de Beniferri F-8 Campo 1(HA)",
      "resultado": null,
      "es_local": false,
      "victoria": null,
      "maps_url": "https://www.google.com/maps/search/?api=1&query=Campo%20de%20F%C3%BAtbol%20Mpal.%20de%20Beniferri%20F-8%20Campo%201%28HA%29%2C%20Valencia%2C%20Espa%C3%B1a"
    },
    {
      "jornada": 7,
      "id_partido": "26450766",
      "fecha": "2026-02-21",
      "hora": "12:30",
      "local": "C.F. Extramurs Valencia 'A'",
      "visitante": "C.F. Històrics de València 'C'",
      "campo": "Campo Tramo III del Turia F-8(HA)",
      "resultado": null,
      "es_local": true,
      "victoria": null,
      "maps_url": "https://www.google.com/maps/search/?api=1&query=Campo%20Tramo%20III%20del%20Turia%20F-8%28HA%29%2C%20Valencia%2C%20Espa%C3%B1a"
    },
    {
      "jornada": 8,
      "id_partido": "26450772",
      "fecha": "2026-03-01",
      "hora": "11:30",
      "local": "C.F. Torre Levante 'A'",
      "visitante": "C.F. Extramurs Valencia 'A'",
      "campo": "Campo Torre Levante-Orriols F-8 Campo 1(HA)",
      "resultado": null,
      "es_local": false,
      "victoria": null,
      "maps_url": "https://www.google.com/maps/search/?api=1&query=Campo%20Torre%20Levante-Orriols%20F-8%20Campo%201%28HA%29%2C%20Valencia%2C%20Espa%C3%B1a"
    },
    {
      "jornada": 9,
      "id_partido": "26450777",
      "fecha": "2026-03-07",
      "hora": "12:30",
      "local": "C.F. Extramurs Valencia 'A'",
      "visitante": "Paterna C.F. 'A'",
      "campo": "Campo Tramo III del Turia F-8(HA)",
      "resultado": null,
      "es_local": true,
      "victoria": null,
      "maps_url": "https://www.google.com/maps/search/?api=1&query=Campo%20Tramo%20III%20del%20Turia%20F-8%28HA%29%2C%20Valencia%2C%20Espa%C3%B1a"
    },
    {
      "jornada": 10,
      "id_partido": "26450779",
      "fecha": "2026-03-14",
      "hora": "12:30",
      "local": "C.F. Extramurs Valencia 'A'",
      "visitante": "Atlètic Vallbonense 'A'",
      "campo": "Campo Tramo III del Turia F-8(HA)",
      "resultado": null,
      "es_local": true,
      "victoria": null,
      "maps_url": "https://www.google.com/maps/search/?api=1&query=Campo%20Tramo%20III%20del%20Turia%20F-8%28HA%29%2C%20Valencia%2C%20Espa%C3%B1a"
    },
    {
      "jornada": 11,
      "id_partido": "26450784",
      "fecha": "2026-03-28",
      "hora": "09:00",
      "local": "Vilamarxant C.F.",
      "visitante": "C.F. Extramurs Valencia 'A'",
      "campo": "Campo Mpal. Germans Albiol F-8 Campo 1 Vilamarxant(HA)",
      "resultado": null,
      "es_local": false,
      "victoria": null,
      "maps_url": "https://www.google.com/maps/search/?api=1&query=Campo%20Mpal.%20Germans%20Albiol%20F-8%20Campo%201%20Vilamarxant%28HA%29%2C%20Valencia%2C%20Espa%C3%B1a"
    },
    {
      "jornada": 12,
      "id_partido": "26450789",
      "fecha": "2026-04-11",
      "hora": "11:30",
      "local": "C.F. Cracks 'B'",
      "visitante": "C.F. Extramurs Valencia 'A'",
      "campo": "Instalaciones Cracks F-8 Campo 4(HA)",
      "resultado": null,
      "es_local": false,
      "victoria": null,
      "maps_url": "https://www.google.com/maps/search/?api=1&query=Instalaciones%20Cracks%20F-8%20Campo%204%28HA%29%2C%20Valencia%2C%20Espa%C3%B1a"
    },
    {
      "jornada": 13,
      "id_partido": "26450795",
      "fecha": "2026-04-18",
      "hora": "12:30",
      "local": "C.F. Extramurs Valencia 'A'",
      "visitante": "Los Silos C.F. - Promises Valencia 'A'",
      "campo": "Campo Tramo III del Turia F-8(HA)",
      "resultado": null,
      "es_local": true,
      "victoria": null,
      "maps_url": "https://www.google.com/maps/search/?api=1&query=Campo%20Tramo%20III%20del%20Turia%20F-8%28HA%29%2C%20Valencia%2C%20Espa%C3%B1a"
    },
    {
      "jornada": 14,
      "id_partido": "26450800",
      "fecha": "2026-04-25",
      "hora": "11:00",
      "local": "S.F.A.C. San Antonio Benagéber 'A'",
      "visitante": "C.F. Extramurs Valencia 'A'",
      "campo": "Campo de Fútbol Mpal. San Ant. de Benageber I F-8 Campo 1(HA)",
      "resultado": null,
      "es_local": false,
      "victoria": null,
      "maps_url": "https://www.google.com/maps/search/?api=1&query=Campo%20de%20F%C3%BAtbol%20Mpal.%20San%20Ant.%20de%20Benageber%20I%20F-8%20Campo%201%28HA%29%2C%20Valencia%2C%20Espa%C3%B1a"
    },
    {
      "jornada": 15,
      "id_partido": "26450806",
      "fecha": "2026-05-09",
      "hora": "12:30",
      "local": "C.F. Extramurs Valencia 'A'",
      "visitante": "C.F. Inter San José Valencia 'C'",
      "campo": "Campo Tramo III del Turia F-8(HA)",
      "resultado": null,
      "es_local": true,
      "victoria": null,
      "maps_url": "https://www.google.com/maps/search/?api=1&query=Campo%20Tramo%20III%20del%20Turia%20F-8%28HA%29%2C%20Valencia%2C%20Espa%C3%B1a"
    },
    {
      "jornada": 16,
      "id_partido": "26450811",
      "fecha": "2026-05-17",
      "hora": "10:15",
      "local": "C.F. Històrics de València 'C'",
      "visitante": "C.F. Extramurs Valencia 'A'",
      "campo": "Poliesportiu Mpal. Marxalenes-Saïdia F-8 Campo 1(HA)",
      "resultado": null,
      "es_local": false,
      "victoria": null,
      "maps_url": "https://www.google.com/maps/search/?api=1&query=Poliesportiu%20Mpal.%20Marxalenes-Sa%C3%AFdia%20F-8%20Campo%201%28HA%29%2C%20Valencia%2C%20Espa%C3%B1a"
    },
    {
      "jornada": 17,
      "id_partido": "26450817",
      "fecha": "2026-05-23",
      "hora": "12:30",
      "local": "C.F. Extramurs Valencia 'A'",
      "visitante": "C.F. Torre Levante 'A'",
      "campo": "Campo Tramo III del Turia F-8(HA)",
      "resultado": null,
      "es_local": true,
      "victoria": null,
      "maps_url": "https://www.google.com/maps/search/?api=1&query=Campo%20Tramo%20III%20del%20Turia%20F-8%28HA%29%2C%20Valencia%2C%20Espa%C3%B1a"
    },
    {
      "jornada": 18,
      "id_partido": "26450822",
      "fecha": "2026-05-29",
      "hora": "19:00",
      "local": "Paterna C.F. 'A'",
      "visitante": "C.F. Extramurs Valencia 'A'",
      "campo": "Estadio Gerardo Salvador F-8 Campo 1 Paterna(HA)",
      "resultado": null,
      "es_local": false,
      "victoria": null,
      "maps_url": "https://www.google.com/maps/search/?api=1&query=Estadio%20Gerardo%20Salvador%20F-8%20Campo%201%20Paterna%28HA%29%2C%20Valencia%2C%20Espa%C3%B1a"
    }
  ]
}